{
    "name": "Weapon Arsenal Deck",
    "width": 63.5,
    "height": 88.9,
    "cards": [
        {
            "id": "rusty-dagger",
            "data": {
                "name": "Rusty Dagger",
                "cost": "2",
                "description": "A weathered blade that's seen better days. Still sharp enough to get the job done.",
                "tier": "Bronze",
                "image": "E:\\Programming\\card-wizard\\example_deck\\images\\bronze_weapon_card_back.png"
            },
            "count": 3,
            "frontStyleId": "weapon-front-bronze",
            "backStyleId": "weapon-back-bronze"
        },
        {
            "id": "wooden-club",
            "data": {
                "name": "Wooden Club",
                "cost": "1",
                "description": "Simple but effective. What it lacks in finesse, it makes up for in reliability.",
                "tier": "Bronze",
                "image": "E:\\Programming\\card-wizard\\example_deck\\images\\bronze_weapon_card_back.png"
            },
            "count": 3,
            "frontStyleId": "weapon-front-bronze",
            "backStyleId": "weapon-back-bronze"
        },
        {
            "id": "hunting-bow",
            "data": {
                "name": "Hunting Bow",
                "cost": "3",
                "description": "A basic bow crafted from ash wood. Perfect for beginners learning the art of archery.",
                "tier": "Bronze",
                "image": "E:\\Programming\\card-wizard\\example_deck\\images\\bronze_weapon_card_back.png"
            },
            "count": 3,
            "frontStyleId": "weapon-front-bronze",
            "backStyleId": "weapon-back-bronze"
        },
        {
            "id": "steel-sword",
            "data": {
                "name": "Steel Sword",
                "cost": "5",
                "description": "Forged by skilled hands, this blade cuts through armor with ease. A warrior's trusted companion.",
                "tier": "Silver",
                "image": "E:\\Programming\\card-wizard\\example_deck\\images\\silver_weapon_card_back.png"
            },
            "count": 3,
            "frontStyleId": "weapon-front-silver",
            "backStyleId": "weapon-back-silver"
        },
        {
            "id": "war-hammer",
            "data": {
                "name": "War Hammer",
                "cost": "6",
                "description": "Heavy and devastating. One swing can shatter shields and break bones.",
                "tier": "Silver",
                "image": "E:\\Programming\\card-wizard\\example_deck\\images\\silver_weapon_card_back.png"
            },
            "count": 3,
            "frontStyleId": "weapon-front-silver",
            "backStyleId": "weapon-back-silver"
        },
        {
            "id": "crossbow",
            "data": {
                "name": "Crossbow",
                "cost": "7",
                "description": "Precision engineering meets deadly force. Pierces plate armor from a hundred paces.",
                "tier": "Silver",
                "image": "E:\\Programming\\card-wizard\\example_deck\\images\\silver_weapon_card_back.png"
            },
            "count": 3,
            "frontStyleId": "weapon-front-silver",
            "backStyleId": "weapon-back-silver"
        },
        {
            "id": "dragon-slayer",
            "data": {
                "name": "Dragon Slayer",
                "cost": "12",
                "description": "Legendary greatsword imbued with ancient magic. Said to have felled the great wyrm Infernus.",
                "tier": "Gold",
                "image": "E:\\Programming\\card-wizard\\example_deck\\images\\gold_weapon_card_back.png"
            },
            "count": 3,
            "frontStyleId": "weapon-front-gold",
            "backStyleId": "weapon-back-gold"
        },
        {
            "id": "thunderstrike-axe",
            "data": {
                "name": "Thunderstrike Axe",
                "cost": "10",
                "description": "Crackling with elemental fury, each strike calls down lightning from the heavens.",
                "tier": "Gold",
                "image": "E:\\Programming\\card-wizard\\example_deck\\images\\gold_weapon_card_back.png"
            },
            "count": 3,
            "frontStyleId": "weapon-front-gold",
            "backStyleId": "weapon-back-gold"
        },
        {
            "id": "phoenix-longbow",
            "data": {
                "name": "Phoenix Longbow",
                "cost": "11",
                "description": "Arrows shot from this bow ignite mid-flight, leaving trails of flame in their wake.",
                "tier": "Gold",
                "image": "E:\\Programming\\card-wizard\\example_deck\\images\\gold_weapon_card_back.png"
            },
            "count": 3,
            "frontStyleId": "weapon-front-gold",
            "backStyleId": "weapon-back-gold"
        }
    ],
    "fields": [
        {
            "name": "name",
            "type": "text"
        },
        {
            "name": "cost",
            "type": "text"
        },
        {
            "name": "description",
            "type": "text"
        },
        {
            "name": "tier",
            "type": "text"
        },
        {
            "name": "image",
            "type": "image"
        }
    ],
    "frontStyles": {
        "weapon-front-bronze": {
            "name": "Bronze Weapon Front",
            "elements": [
                {
                    "id": "name-bronze",
                    "type": "text",
                    "field": "name",
                    "x": 5,
                    "y": 5,
                    "width": 53.5,
                    "height": 10,
                    "fontSize": 18,
                    "color": "#8B4513",
                    "fontFamily": "Georgia, serif"
                },
                {
                    "id": "cost-bronze",
                    "type": "text",
                    "field": "cost",
                    "x": 50,
                    "y": 17,
                    "width": 8.5,
                    "height": 8,
                    "fontSize": 16,
                    "color": "#CD7F32",
                    "fontFamily": "Courier New, monospace"
                },
                {
                    "id": "cost-label-bronze",
                    "type": "text",
                    "staticText": "💰",
                    "x": 45,
                    "y": 17,
                    "width": 5,
                    "height": 8,
                    "fontSize": 14,
                    "color": "#FFD700"
                },
                {
                    "id": "desc-bronze",
                    "type": "text",
                    "field": "description",
                    "x": 5,
                    "y": 27,
                    "width": 53.5,
                    "height": 30,
                    "fontSize": 11,
                    "color": "#333333",
                    "fontFamily": "Verdana, sans-serif"
                },
                {
                    "id": "tier-bronze",
                    "type": "text",
                    "field": "tier",
                    "x": 5,
                    "y": 78,
                    "width": 20,
                    "height": 6,
                    "fontSize": 10,
                    "color": "#CD7F32",
                    "fontFamily": "Arial, sans-serif"
                }
            ]
        },
        "weapon-front-silver": {
            "name": "Silver Weapon Front",
            "elements": [
                {
                    "id": "name-silver",
                    "type": "text",
                    "field": "name",
                    "x": 5,
                    "y": 5,
                    "width": 53.5,
                    "height": 10,
                    "fontSize": 18,
                    "color": "#2F4F4F",
                    "fontFamily": "Times New Roman, serif"
                },
                {
                    "id": "cost-silver",
                    "type": "text",
                    "field": "cost",
                    "x": 50,
                    "y": 17,
                    "width": 8.5,
                    "height": 8,
                    "fontSize": 16,
                    "color": "#C0C0C0",
                    "fontFamily": "Georgia, serif"
                },
                {
                    "id": "cost-label-silver",
                    "type": "text",
                    "staticText": "💰",
                    "x": 45,
                    "y": 17,
                    "width": 5,
                    "height": 8,
                    "fontSize": 14,
                    "color": "#FFD700"
                },
                {
                    "id": "desc-silver",
                    "type": "text",
                    "field": "description",
                    "x": 5,
                    "y": 27,
                    "width": 53.5,
                    "height": 30,
                    "fontSize": 11,
                    "color": "#1C1C1C",
                    "fontFamily": "Helvetica, sans-serif"
                },
                {
                    "id": "tier-silver",
                    "type": "text",
                    "field": "tier",
                    "x": 5,
                    "y": 78,
                    "width": 20,
                    "height": 6,
                    "fontSize": 10,
                    "color": "#C0C0C0",
                    "fontFamily": "Courier New, monospace"
                }
            ]
        },
        "weapon-front-gold": {
            "name": "Gold Weapon Front",
            "elements": [
                {
                    "id": "name-gold",
                    "type": "text",
                    "field": "name",
                    "x": 5,
                    "y": 5,
                    "width": 53.5,
                    "height": 10,
                    "fontSize": 20,
                    "color": "#8B0000",
                    "fontFamily": "Verdana, sans-serif"
                },
                {
                    "id": "cost-gold",
                    "type": "text",
                    "field": "cost",
                    "x": 50,
                    "y": 17,
                    "width": 8.5,
                    "height": 8,
                    "fontSize": 18,
                    "color": "#FFD700",
                    "fontFamily": "Times New Roman, serif"
                },
                {
                    "id": "cost-label-gold",
                    "type": "text",
                    "staticText": "💰",
                    "x": 45,
                    "y": 17,
                    "width": 5,
                    "height": 8,
                    "fontSize": 14,
                    "color": "#FFD700"
                },
                {
                    "id": "desc-gold",
                    "type": "text",
                    "field": "description",
                    "x": 5,
                    "y": 27,
                    "width": 53.5,
                    "height": 30,
                    "fontSize": 12,
                    "color": "#000000",
                    "fontFamily": "Georgia, serif"
                },
                {
                    "id": "tier-gold",
                    "type": "text",
                    "field": "tier",
                    "x": 5,
                    "y": 78,
                    "width": 20,
                    "height": 6,
                    "fontSize": 11,
                    "color": "#FFD700",
                    "fontFamily": "Helvetica, sans-serif"
                }
            ]
        }
    },
    "backStyles": {
        "weapon-back-bronze": {
            "name": "Bronze Weapon Back",
            "elements": [
                {
                    "id": "back-image-bronze",
                    "type": "image",
                    "field": "image",
                    "x": 0,
                    "y": 0,
                    "width": 63.5,
                    "height": 88.9,
                    "objectFit": "cover"
                }
            ]
        },
        "weapon-back-silver": {
            "name": "Silver Weapon Back",
            "elements": [
                {
                    "id": "back-image-silver",
                    "type": "image",
                    "field": "image",
                    "x": 0,
                    "y": 0,
                    "width": 63.5,
                    "height": 88.9,
                    "objectFit": "cover"
                }
            ]
        },
        "weapon-back-gold": {
            "name": "Gold Weapon Back",
            "elements": [
                {
                    "id": "back-image-gold",
                    "type": "image",
                    "field": "image",
                    "x": 0,
                    "y": 0,
                    "width": 63.5,
                    "height": 88.9,
                    "objectFit": "cover"
                }
            ]
        }
    },
    "customFonts": []
}